[{"arguments":["clang","-Wno-documentation-unknown-command","-Wno-unknown-warning-option","-Wno-unknown-pragmas","-nostdinc","-nostdinc++","-g","-std=gnu++1z","-Wall","-Wextra","-Wextra","-fexceptions","-mthreads","-fsyntax-only","-m64","--target=x86_64-w64-mingw32","-DUNICODE","-D_UNICODE","-DWIN32","-DMINGW_HAS_SECURE_API","-DQT_QML_DEBUG","-DQT_NO_DEBUG","-DQT_WIDGETS_LIB","-DQT_GUI_LIB","-DQT_CORE_LIB","-DQT_NEEDS_QMAIN","-DQ_CREATOR_RUN","-DQT_ANNOTATE_FUNCTION(x)=__attribute__((annotate(#x)))","-IC:\\QtInstall\\Tools\\QtCreator\\share\\qtcreator\\cplusplus\\wrappedMingwHeaders","-IC:\\QtInstall\\Tools\\QtCreator\\share\\qtcreator\\cplusplus\\wrappedQtHeaders","-IC:\\QtInstall\\Tools\\QtCreator\\share\\qtcreator\\cplusplus\\wrappedQtHeaders\\QtCore","-IC:\\ADW\\Dev\\C++\\QT\\MingWang\\02_Event\\src","-IC:\\QtInstall\\6.2.4\\mingw_64\\include","-IC:\\QtInstall\\6.2.4\\mingw_64\\include\\QtWidgets","-IC:\\QtInstall\\6.2.4\\mingw_64\\include\\QtGui","-IC:\\QtInstall\\6.2.4\\mingw_64\\include\\QtCore","-IC:\\ADW\\Dev\\C++\\QT\\MingWang\\02_Event\\Event\\build\\Desktop_Qt_6_2_4_MinGW_64_bit-Profile\\release","-IC:\\ADW\\Dev\\C++\\QT\\MingWang\\02_Event\\Event\\build\\Desktop_Qt_6_2_4_MinGW_64_bit-Profile","-IC:\\QtInstall\\6.2.4\\mingw_64\\mkspecs\\win32-g++","-isystem","C:\\QtInstall\\Tools\\mingw1120_64\\lib\\gcc\\x86_64-w64-mingw32\\11.2.0\\include\\c++","-isystem","C:\\QtInstall\\Tools\\mingw1120_64\\lib\\gcc\\x86_64-w64-mingw32\\11.2.0\\include\\c++\\x86_64-w64-mingw32","-isystem","C:\\QtInstall\\Tools\\mingw1120_64\\lib\\gcc\\x86_64-w64-mingw32\\11.2.0\\include\\c++\\backward","-isystem","C:\\QtInstall\\Tools\\QtCreator\\bin\\clang\\lib\\clang\\17\\include","-isystem","C:\\QtInstall\\Tools\\mingw1120_64\\x86_64-w64-mingw32\\include","-fmessage-length=0","-fdiagnostics-show-note-include-stack","-fretain-comments-from-system-headers","-fmacro-backtrace-limit=0","-ferror-limit=1000","-x","c++","C:\\ADW\\Dev\\C++\\QT\\MingWang\\02_Event\\src\\demo00_event.cpp"],"directory":"C:/ADW/Dev/C++/QT/MingWang/02_Event/Event/build/Desktop_Qt_6_2_4_MinGW_64_bit-Profile/.qtc_clangd","file":"C:/ADW/Dev/C++/QT/MingWang/02_Event/src/demo00_event.cpp"},{"arguments":["clang","-Wno-documentation-unknown-command","-Wno-unknown-warning-option","-Wno-unknown-pragmas","-nostdinc","-nostdinc++","-g","-std=gnu++1z","-Wall","-Wextra","-Wextra","-fexceptions","-mthreads","-fsyntax-only","-m64","--target=x86_64-w64-mingw32","-DUNICODE","-D_UNICODE","-DWIN32","-DMINGW_HAS_SECURE_API","-DQT_QML_DEBUG","-DQT_NO_DEBUG","-DQT_WIDGETS_LIB","-DQT_GUI_LIB","-DQT_CORE_LIB","-DQT_NEEDS_QMAIN","-DQ_CREATOR_RUN","-DQT_ANNOTATE_FUNCTION(x)=__attribute__((annotate(#x)))","-IC:\\QtInstall\\Tools\\QtCreator\\share\\qtcreator\\cplusplus\\wrappedMingwHeaders","-IC:\\QtInstall\\Tools\\QtCreator\\share\\qtcreator\\cplusplus\\wrappedQtHeaders","-IC:\\QtInstall\\Tools\\QtCreator\\share\\qtcreator\\cplusplus\\wrappedQtHeaders\\QtCore","-IC:\\ADW\\Dev\\C++\\QT\\MingWang\\02_Event\\src","-IC:\\QtInstall\\6.2.4\\mingw_64\\include","-IC:\\QtInstall\\6.2.4\\mingw_64\\include\\QtWidgets","-IC:\\QtInstall\\6.2.4\\mingw_64\\include\\QtGui","-IC:\\QtInstall\\6.2.4\\mingw_64\\include\\QtCore","-IC:\\ADW\\Dev\\C++\\QT\\MingWang\\02_Event\\Event\\build\\Desktop_Qt_6_2_4_MinGW_64_bit-Profile\\release","-IC:\\ADW\\Dev\\C++\\QT\\MingWang\\02_Event\\Event\\build\\Desktop_Qt_6_2_4_MinGW_64_bit-Profile","-IC:\\QtInstall\\6.2.4\\mingw_64\\mkspecs\\win32-g++","-isystem","C:\\QtInstall\\Tools\\mingw1120_64\\lib\\gcc\\x86_64-w64-mingw32\\11.2.0\\include\\c++","-isystem","C:\\QtInstall\\Tools\\mingw1120_64\\lib\\gcc\\x86_64-w64-mingw32\\11.2.0\\include\\c++\\x86_64-w64-mingw32","-isystem","C:\\QtInstall\\Tools\\mingw1120_64\\lib\\gcc\\x86_64-w64-mingw32\\11.2.0\\include\\c++\\backward","-isystem","C:\\QtInstall\\Tools\\QtCreator\\bin\\clang\\lib\\clang\\17\\include","-isystem","C:\\QtInstall\\Tools\\mingw1120_64\\x86_64-w64-mingw32\\include","-fmessage-length=0","-fdiagnostics-show-note-include-stack","-fretain-comments-from-system-headers","-fmacro-backtrace-limit=0","-ferror-limit=1000","-x","c++","C:\\ADW\\Dev\\C++\\QT\\MingWang\\02_Event\\src\\demo01_mouse_event.cpp"],"directory":"C:/ADW/Dev/C++/QT/MingWang/02_Event/Event/build/Desktop_Qt_6_2_4_MinGW_64_bit-Profile/.qtc_clangd","file":"C:/ADW/Dev/C++/QT/MingWang/02_Event/src/demo01_mouse_event.cpp"},{"arguments":["clang","-Wno-documentation-unknown-command","-Wno-unknown-warning-option","-Wno-unknown-pragmas","-nostdinc","-nostdinc++","-g","-std=gnu++1z","-Wall","-Wextra","-Wextra","-fexceptions","-mthreads","-fsyntax-only","-m64","--target=x86_64-w64-mingw32","-DUNICODE","-D_UNICODE","-DWIN32","-DMINGW_HAS_SECURE_API","-DQT_QML_DEBUG","-DQT_NO_DEBUG","-DQT_WIDGETS_LIB","-DQT_GUI_LIB","-DQT_CORE_LIB","-DQT_NEEDS_QMAIN","-DQ_CREATOR_RUN","-DQT_ANNOTATE_FUNCTION(x)=__attribute__((annotate(#x)))","-IC:\\QtInstall\\Tools\\QtCreator\\share\\qtcreator\\cplusplus\\wrappedMingwHeaders","-IC:\\QtInstall\\Tools\\QtCreator\\share\\qtcreator\\cplusplus\\wrappedQtHeaders","-IC:\\QtInstall\\Tools\\QtCreator\\share\\qtcreator\\cplusplus\\wrappedQtHeaders\\QtCore","-IC:\\ADW\\Dev\\C++\\QT\\MingWang\\02_Event\\src","-IC:\\QtInstall\\6.2.4\\mingw_64\\include","-IC:\\QtInstall\\6.2.4\\mingw_64\\include\\QtWidgets","-IC:\\QtInstall\\6.2.4\\mingw_64\\include\\QtGui","-IC:\\QtInstall\\6.2.4\\mingw_64\\include\\QtCore","-IC:\\ADW\\Dev\\C++\\QT\\MingWang\\02_Event\\Event\\build\\Desktop_Qt_6_2_4_MinGW_64_bit-Profile\\release","-IC:\\ADW\\Dev\\C++\\QT\\MingWang\\02_Event\\Event\\build\\Desktop_Qt_6_2_4_MinGW_64_bit-Profile","-IC:\\QtInstall\\6.2.4\\mingw_64\\mkspecs\\win32-g++","-isystem","C:\\QtInstall\\Tools\\mingw1120_64\\lib\\gcc\\x86_64-w64-mingw32\\11.2.0\\include\\c++","-isystem","C:\\QtInstall\\Tools\\mingw1120_64\\lib\\gcc\\x86_64-w64-mingw32\\11.2.0\\include\\c++\\x86_64-w64-mingw32","-isystem","C:\\QtInstall\\Tools\\mingw1120_64\\lib\\gcc\\x86_64-w64-mingw32\\11.2.0\\include\\c++\\backward","-isystem","C:\\QtInstall\\Tools\\QtCreator\\bin\\clang\\lib\\clang\\17\\include","-isystem","C:\\QtInstall\\Tools\\mingw1120_64\\x86_64-w64-mingw32\\include","-fmessage-length=0","-fdiagnostics-show-note-include-stack","-fretain-comments-from-system-headers","-fmacro-backtrace-limit=0","-ferror-limit=1000","-x","c++","C:\\ADW\\Dev\\C++\\QT\\MingWang\\02_Event\\src\\demo02_keyboard_event.cpp"],"directory":"C:/ADW/Dev/C++/QT/MingWang/02_Event/Event/build/Desktop_Qt_6_2_4_MinGW_64_bit-Profile/.qtc_clangd","file":"C:/ADW/Dev/C++/QT/MingWang/02_Event/src/demo02_keyboard_event.cpp"},{"arguments":["clang","-Wno-documentation-unknown-command","-Wno-unknown-warning-option","-Wno-unknown-pragmas","-nostdinc","-nostdinc++","-g","-std=gnu++1z","-Wall","-Wextra","-Wextra","-fexceptions","-mthreads","-fsyntax-only","-m64","--target=x86_64-w64-mingw32","-DUNICODE","-D_UNICODE","-DWIN32","-DMINGW_HAS_SECURE_API","-DQT_QML_DEBUG","-DQT_NO_DEBUG","-DQT_WIDGETS_LIB","-DQT_GUI_LIB","-DQT_CORE_LIB","-DQT_NEEDS_QMAIN","-DQ_CREATOR_RUN","-DQT_ANNOTATE_FUNCTION(x)=__attribute__((annotate(#x)))","-IC:\\QtInstall\\Tools\\QtCreator\\share\\qtcreator\\cplusplus\\wrappedMingwHeaders","-IC:\\QtInstall\\Tools\\QtCreator\\share\\qtcreator\\cplusplus\\wrappedQtHeaders","-IC:\\QtInstall\\Tools\\QtCreator\\share\\qtcreator\\cplusplus\\wrappedQtHeaders\\QtCore","-IC:\\ADW\\Dev\\C++\\QT\\MingWang\\02_Event\\src","-IC:\\QtInstall\\6.2.4\\mingw_64\\include","-IC:\\QtInstall\\6.2.4\\mingw_64\\include\\QtWidgets","-IC:\\QtInstall\\6.2.4\\mingw_64\\include\\QtGui","-IC:\\QtInstall\\6.2.4\\mingw_64\\include\\QtCore","-IC:\\ADW\\Dev\\C++\\QT\\MingWang\\02_Event\\Event\\build\\Desktop_Qt_6_2_4_MinGW_64_bit-Profile\\release","-IC:\\ADW\\Dev\\C++\\QT\\MingWang\\02_Event\\Event\\build\\Desktop_Qt_6_2_4_MinGW_64_bit-Profile","-IC:\\QtInstall\\6.2.4\\mingw_64\\mkspecs\\win32-g++","-isystem","C:\\QtInstall\\Tools\\mingw1120_64\\lib\\gcc\\x86_64-w64-mingw32\\11.2.0\\include\\c++","-isystem","C:\\QtInstall\\Tools\\mingw1120_64\\lib\\gcc\\x86_64-w64-mingw32\\11.2.0\\include\\c++\\x86_64-w64-mingw32","-isystem","C:\\QtInstall\\Tools\\mingw1120_64\\lib\\gcc\\x86_64-w64-mingw32\\11.2.0\\include\\c++\\backward","-isystem","C:\\QtInstall\\Tools\\QtCreator\\bin\\clang\\lib\\clang\\17\\include","-isystem","C:\\QtInstall\\Tools\\mingw1120_64\\x86_64-w64-mingw32\\include","-fmessage-length=0","-fdiagnostics-show-note-include-stack","-fretain-comments-from-system-headers","-fmacro-backtrace-limit=0","-ferror-limit=1000","-x","c++","C:\\ADW\\Dev\\C++\\QT\\MingWang\\02_Event\\src\\demo03_timer_event.cpp"],"directory":"C:/ADW/Dev/C++/QT/MingWang/02_Event/Event/build/Desktop_Qt_6_2_4_MinGW_64_bit-Profile/.qtc_clangd","file":"C:/ADW/Dev/C++/QT/MingWang/02_Event/src/demo03_timer_event.cpp"},{"arguments":["clang","-Wno-documentation-unknown-command","-Wno-unknown-warning-option","-Wno-unknown-pragmas","-nostdinc","-nostdinc++","-g","-std=gnu++1z","-Wall","-Wextra","-Wextra","-fexceptions","-mthreads","-fsyntax-only","-m64","--target=x86_64-w64-mingw32","-DUNICODE","-D_UNICODE","-DWIN32","-DMINGW_HAS_SECURE_API","-DQT_QML_DEBUG","-DQT_NO_DEBUG","-DQT_WIDGETS_LIB","-DQT_GUI_LIB","-DQT_CORE_LIB","-DQT_NEEDS_QMAIN","-DQ_CREATOR_RUN","-DQT_ANNOTATE_FUNCTION(x)=__attribute__((annotate(#x)))","-IC:\\QtInstall\\Tools\\QtCreator\\share\\qtcreator\\cplusplus\\wrappedMingwHeaders","-IC:\\QtInstall\\Tools\\QtCreator\\share\\qtcreator\\cplusplus\\wrappedQtHeaders","-IC:\\QtInstall\\Tools\\QtCreator\\share\\qtcreator\\cplusplus\\wrappedQtHeaders\\QtCore","-IC:\\ADW\\Dev\\C++\\QT\\MingWang\\02_Event\\src","-IC:\\QtInstall\\6.2.4\\mingw_64\\include","-IC:\\QtInstall\\6.2.4\\mingw_64\\include\\QtWidgets","-IC:\\QtInstall\\6.2.4\\mingw_64\\include\\QtGui","-IC:\\QtInstall\\6.2.4\\mingw_64\\include\\QtCore","-IC:\\ADW\\Dev\\C++\\QT\\MingWang\\02_Event\\Event\\build\\Desktop_Qt_6_2_4_MinGW_64_bit-Profile\\release","-IC:\\ADW\\Dev\\C++\\QT\\MingWang\\02_Event\\Event\\build\\Desktop_Qt_6_2_4_MinGW_64_bit-Profile","-IC:\\QtInstall\\6.2.4\\mingw_64\\mkspecs\\win32-g++","-isystem","C:\\QtInstall\\Tools\\mingw1120_64\\lib\\gcc\\x86_64-w64-mingw32\\11.2.0\\include\\c++","-isystem","C:\\QtInstall\\Tools\\mingw1120_64\\lib\\gcc\\x86_64-w64-mingw32\\11.2.0\\include\\c++\\x86_64-w64-mingw32","-isystem","C:\\QtInstall\\Tools\\mingw1120_64\\lib\\gcc\\x86_64-w64-mingw32\\11.2.0\\include\\c++\\backward","-isystem","C:\\QtInstall\\Tools\\QtCreator\\bin\\clang\\lib\\clang\\17\\include","-isystem","C:\\QtInstall\\Tools\\mingw1120_64\\x86_64-w64-mingw32\\include","-fmessage-length=0","-fdiagnostics-show-note-include-stack","-fretain-comments-from-system-headers","-fmacro-backtrace-limit=0","-ferror-limit=1000","-x","c++","C:\\ADW\\Dev\\C++\\QT\\MingWang\\02_Event\\src\\demo04_drag_event.cpp"],"directory":"C:/ADW/Dev/C++/QT/MingWang/02_Event/Event/build/Desktop_Qt_6_2_4_MinGW_64_bit-Profile/.qtc_clangd","file":"C:/ADW/Dev/C++/QT/MingWang/02_Event/src/demo04_drag_event.cpp"},{"arguments":["clang","-Wno-documentation-unknown-command","-Wno-unknown-warning-option","-Wno-unknown-pragmas","-nostdinc","-nostdinc++","-g","-std=gnu++1z","-Wall","-Wextra","-Wextra","-fexceptions","-mthreads","-fsyntax-only","-m64","--target=x86_64-w64-mingw32","-DUNICODE","-D_UNICODE","-DWIN32","-DMINGW_HAS_SECURE_API","-DQT_QML_DEBUG","-DQT_NO_DEBUG","-DQT_WIDGETS_LIB","-DQT_GUI_LIB","-DQT_CORE_LIB","-DQT_NEEDS_QMAIN","-DQ_CREATOR_RUN","-DQT_ANNOTATE_FUNCTION(x)=__attribute__((annotate(#x)))","-IC:\\QtInstall\\Tools\\QtCreator\\share\\qtcreator\\cplusplus\\wrappedMingwHeaders","-IC:\\QtInstall\\Tools\\QtCreator\\share\\qtcreator\\cplusplus\\wrappedQtHeaders","-IC:\\QtInstall\\Tools\\QtCreator\\share\\qtcreator\\cplusplus\\wrappedQtHeaders\\QtCore","-IC:\\ADW\\Dev\\C++\\QT\\MingWang\\02_Event\\src","-IC:\\QtInstall\\6.2.4\\mingw_64\\include","-IC:\\QtInstall\\6.2.4\\mingw_64\\include\\QtWidgets","-IC:\\QtInstall\\6.2.4\\mingw_64\\include\\QtGui","-IC:\\QtInstall\\6.2.4\\mingw_64\\include\\QtCore","-IC:\\ADW\\Dev\\C++\\QT\\MingWang\\02_Event\\Event\\build\\Desktop_Qt_6_2_4_MinGW_64_bit-Profile\\release","-IC:\\ADW\\Dev\\C++\\QT\\MingWang\\02_Event\\Event\\build\\Desktop_Qt_6_2_4_MinGW_64_bit-Profile","-IC:\\QtInstall\\6.2.4\\mingw_64\\mkspecs\\win32-g++","-isystem","C:\\QtInstall\\Tools\\mingw1120_64\\lib\\gcc\\x86_64-w64-mingw32\\11.2.0\\include\\c++","-isystem","C:\\QtInstall\\Tools\\mingw1120_64\\lib\\gcc\\x86_64-w64-mingw32\\11.2.0\\include\\c++\\x86_64-w64-mingw32","-isystem","C:\\QtInstall\\Tools\\mingw1120_64\\lib\\gcc\\x86_64-w64-mingw32\\11.2.0\\include\\c++\\backward","-isystem","C:\\QtInstall\\Tools\\QtCreator\\bin\\clang\\lib\\clang\\17\\include","-isystem","C:\\QtInstall\\Tools\\mingw1120_64\\x86_64-w64-mingw32\\include","-fmessage-length=0","-fdiagnostics-show-note-include-stack","-fretain-comments-from-system-headers","-fmacro-backtrace-limit=0","-ferror-limit=1000","-x","c++","C:\\ADW\\Dev\\C++\\QT\\MingWang\\02_Event\\src\\demo05_paint_event.cpp"],"directory":"C:/ADW/Dev/C++/QT/MingWang/02_Event/Event/build/Desktop_Qt_6_2_4_MinGW_64_bit-Profile/.qtc_clangd","file":"C:/ADW/Dev/C++/QT/MingWang/02_Event/src/demo05_paint_event.cpp"},{"arguments":["clang","-Wno-documentation-unknown-command","-Wno-unknown-warning-option","-Wno-unknown-pragmas","-nostdinc","-nostdinc++","-g","-std=gnu++1z","-Wall","-Wextra","-Wextra","-fexceptions","-mthreads","-fsyntax-only","-m64","--target=x86_64-w64-mingw32","-DUNICODE","-D_UNICODE","-DWIN32","-DMINGW_HAS_SECURE_API","-DQT_QML_DEBUG","-DQT_NO_DEBUG","-DQT_WIDGETS_LIB","-DQT_GUI_LIB","-DQT_CORE_LIB","-DQT_NEEDS_QMAIN","-DQ_CREATOR_RUN","-DQT_ANNOTATE_FUNCTION(x)=__attribute__((annotate(#x)))","-IC:\\QtInstall\\Tools\\QtCreator\\share\\qtcreator\\cplusplus\\wrappedMingwHeaders","-IC:\\QtInstall\\Tools\\QtCreator\\share\\qtcreator\\cplusplus\\wrappedQtHeaders","-IC:\\QtInstall\\Tools\\QtCreator\\share\\qtcreator\\cplusplus\\wrappedQtHeaders\\QtCore","-IC:\\ADW\\Dev\\C++\\QT\\MingWang\\02_Event\\src","-IC:\\QtInstall\\6.2.4\\mingw_64\\include","-IC:\\QtInstall\\6.2.4\\mingw_64\\include\\QtWidgets","-IC:\\QtInstall\\6.2.4\\mingw_64\\include\\QtGui","-IC:\\QtInstall\\6.2.4\\mingw_64\\include\\QtCore","-IC:\\ADW\\Dev\\C++\\QT\\MingWang\\02_Event\\Event\\build\\Desktop_Qt_6_2_4_MinGW_64_bit-Profile\\release","-IC:\\ADW\\Dev\\C++\\QT\\MingWang\\02_Event\\Event\\build\\Desktop_Qt_6_2_4_MinGW_64_bit-Profile","-IC:\\QtInstall\\6.2.4\\mingw_64\\mkspecs\\win32-g++","-isystem","C:\\QtInstall\\Tools\\mingw1120_64\\lib\\gcc\\x86_64-w64-mingw32\\11.2.0\\include\\c++","-isystem","C:\\QtInstall\\Tools\\mingw1120_64\\lib\\gcc\\x86_64-w64-mingw32\\11.2.0\\include\\c++\\x86_64-w64-mingw32","-isystem","C:\\QtInstall\\Tools\\mingw1120_64\\lib\\gcc\\x86_64-w64-mingw32\\11.2.0\\include\\c++\\backward","-isystem","C:\\QtInstall\\Tools\\QtCreator\\bin\\clang\\lib\\clang\\17\\include","-isystem","C:\\QtInstall\\Tools\\mingw1120_64\\x86_64-w64-mingw32\\include","-fmessage-length=0","-fdiagnostics-show-note-include-stack","-fretain-comments-from-system-headers","-fmacro-backtrace-limit=0","-ferror-limit=1000","-x","c++","C:\\ADW\\Dev\\C++\\QT\\MingWang\\02_Event\\src\\demo06_context_menu_event.cpp"],"directory":"C:/ADW/Dev/C++/QT/MingWang/02_Event/Event/build/Desktop_Qt_6_2_4_MinGW_64_bit-Profile/.qtc_clangd","file":"C:/ADW/Dev/C++/QT/MingWang/02_Event/src/demo06_context_menu_event.cpp"},{"arguments":["clang","-Wno-documentation-unknown-command","-Wno-unknown-warning-option","-Wno-unknown-pragmas","-nostdinc","-nostdinc++","-g","-std=gnu++1z","-Wall","-Wextra","-Wextra","-fexceptions","-mthreads","-fsyntax-only","-m64","--target=x86_64-w64-mingw32","-DUNICODE","-D_UNICODE","-DWIN32","-DMINGW_HAS_SECURE_API","-DQT_QML_DEBUG","-DQT_NO_DEBUG","-DQT_WIDGETS_LIB","-DQT_GUI_LIB","-DQT_CORE_LIB","-DQT_NEEDS_QMAIN","-DQ_CREATOR_RUN","-DQT_ANNOTATE_FUNCTION(x)=__attribute__((annotate(#x)))","-IC:\\QtInstall\\Tools\\QtCreator\\share\\qtcreator\\cplusplus\\wrappedMingwHeaders","-IC:\\QtInstall\\Tools\\QtCreator\\share\\qtcreator\\cplusplus\\wrappedQtHeaders","-IC:\\QtInstall\\Tools\\QtCreator\\share\\qtcreator\\cplusplus\\wrappedQtHeaders\\QtCore","-IC:\\ADW\\Dev\\C++\\QT\\MingWang\\02_Event\\src","-IC:\\QtInstall\\6.2.4\\mingw_64\\include","-IC:\\QtInstall\\6.2.4\\mingw_64\\include\\QtWidgets","-IC:\\QtInstall\\6.2.4\\mingw_64\\include\\QtGui","-IC:\\QtInstall\\6.2.4\\mingw_64\\include\\QtCore","-IC:\\ADW\\Dev\\C++\\QT\\MingWang\\02_Event\\Event\\build\\Desktop_Qt_6_2_4_MinGW_64_bit-Profile\\release","-IC:\\ADW\\Dev\\C++\\QT\\MingWang\\02_Event\\Event\\build\\Desktop_Qt_6_2_4_MinGW_64_bit-Profile","-IC:\\QtInstall\\6.2.4\\mingw_64\\mkspecs\\win32-g++","-isystem","C:\\QtInstall\\Tools\\mingw1120_64\\lib\\gcc\\x86_64-w64-mingw32\\11.2.0\\include\\c++","-isystem","C:\\QtInstall\\Tools\\mingw1120_64\\lib\\gcc\\x86_64-w64-mingw32\\11.2.0\\include\\c++\\x86_64-w64-mingw32","-isystem","C:\\QtInstall\\Tools\\mingw1120_64\\lib\\gcc\\x86_64-w64-mingw32\\11.2.0\\include\\c++\\backward","-isystem","C:\\QtInstall\\Tools\\QtCreator\\bin\\clang\\lib\\clang\\17\\include","-isystem","C:\\QtInstall\\Tools\\mingw1120_64\\x86_64-w64-mingw32\\include","-fmessage-length=0","-fdiagnostics-show-note-include-stack","-fretain-comments-from-system-headers","-fmacro-backtrace-limit=0","-ferror-limit=1000","-x","c++","C:\\ADW\\Dev\\C++\\QT\\MingWang\\02_Event\\src\\demo07_event_propagate_process.cpp"],"directory":"C:/ADW/Dev/C++/QT/MingWang/02_Event/Event/build/Desktop_Qt_6_2_4_MinGW_64_bit-Profile/.qtc_clangd","file":"C:/ADW/Dev/C++/QT/MingWang/02_Event/src/demo07_event_propagate_process.cpp"},{"arguments":["clang","-Wno-documentation-unknown-command","-Wno-unknown-warning-option","-Wno-unknown-pragmas","-nostdinc","-nostdinc++","-g","-std=gnu++1z","-Wall","-Wextra","-Wextra","-fexceptions","-mthreads","-fsyntax-only","-m64","--target=x86_64-w64-mingw32","-DUNICODE","-D_UNICODE","-DWIN32","-DMINGW_HAS_SECURE_API","-DQT_QML_DEBUG","-DQT_NO_DEBUG","-DQT_WIDGETS_LIB","-DQT_GUI_LIB","-DQT_CORE_LIB","-DQT_NEEDS_QMAIN","-DQ_CREATOR_RUN","-DQT_ANNOTATE_FUNCTION(x)=__attribute__((annotate(#x)))","-IC:\\QtInstall\\Tools\\QtCreator\\share\\qtcreator\\cplusplus\\wrappedMingwHeaders","-IC:\\QtInstall\\Tools\\QtCreator\\share\\qtcreator\\cplusplus\\wrappedQtHeaders","-IC:\\QtInstall\\Tools\\QtCreator\\share\\qtcreator\\cplusplus\\wrappedQtHeaders\\QtCore","-IC:\\ADW\\Dev\\C++\\QT\\MingWang\\02_Event\\src","-IC:\\QtInstall\\6.2.4\\mingw_64\\include","-IC:\\QtInstall\\6.2.4\\mingw_64\\include\\QtWidgets","-IC:\\QtInstall\\6.2.4\\mingw_64\\include\\QtGui","-IC:\\QtInstall\\6.2.4\\mingw_64\\include\\QtCore","-IC:\\ADW\\Dev\\C++\\QT\\MingWang\\02_Event\\Event\\build\\Desktop_Qt_6_2_4_MinGW_64_bit-Profile\\release","-IC:\\ADW\\Dev\\C++\\QT\\MingWang\\02_Event\\Event\\build\\Desktop_Qt_6_2_4_MinGW_64_bit-Profile","-IC:\\QtInstall\\6.2.4\\mingw_64\\mkspecs\\win32-g++","-isystem","C:\\QtInstall\\Tools\\mingw1120_64\\lib\\gcc\\x86_64-w64-mingw32\\11.2.0\\include\\c++","-isystem","C:\\QtInstall\\Tools\\mingw1120_64\\lib\\gcc\\x86_64-w64-mingw32\\11.2.0\\include\\c++\\x86_64-w64-mingw32","-isystem","C:\\QtInstall\\Tools\\mingw1120_64\\lib\\gcc\\x86_64-w64-mingw32\\11.2.0\\include\\c++\\backward","-isystem","C:\\QtInstall\\Tools\\QtCreator\\bin\\clang\\lib\\clang\\17\\include","-isystem","C:\\QtInstall\\Tools\\mingw1120_64\\x86_64-w64-mingw32\\include","-fmessage-length=0","-fdiagnostics-show-note-include-stack","-fretain-comments-from-system-headers","-fmacro-backtrace-limit=0","-ferror-limit=1000","-x","c++","C:\\ADW\\Dev\\C++\\QT\\MingWang\\02_Event\\src\\demobase.cpp"],"directory":"C:/ADW/Dev/C++/QT/MingWang/02_Event/Event/build/Desktop_Qt_6_2_4_MinGW_64_bit-Profile/.qtc_clangd","file":"C:/ADW/Dev/C++/QT/MingWang/02_Event/src/demobase.cpp"},{"arguments":["clang","-Wno-documentation-unknown-command","-Wno-unknown-warning-option","-Wno-unknown-pragmas","-nostdinc","-nostdinc++","-g","-std=gnu++1z","-Wall","-Wextra","-Wextra","-fexceptions","-mthreads","-fsyntax-only","-m64","--target=x86_64-w64-mingw32","-DUNICODE","-D_UNICODE","-DWIN32","-DMINGW_HAS_SECURE_API","-DQT_QML_DEBUG","-DQT_NO_DEBUG","-DQT_WIDGETS_LIB","-DQT_GUI_LIB","-DQT_CORE_LIB","-DQT_NEEDS_QMAIN","-DQ_CREATOR_RUN","-DQT_ANNOTATE_FUNCTION(x)=__attribute__((annotate(#x)))","-IC:\\QtInstall\\Tools\\QtCreator\\share\\qtcreator\\cplusplus\\wrappedMingwHeaders","-IC:\\QtInstall\\Tools\\QtCreator\\share\\qtcreator\\cplusplus\\wrappedQtHeaders","-IC:\\QtInstall\\Tools\\QtCreator\\share\\qtcreator\\cplusplus\\wrappedQtHeaders\\QtCore","-IC:\\ADW\\Dev\\C++\\QT\\MingWang\\02_Event\\src","-IC:\\QtInstall\\6.2.4\\mingw_64\\include","-IC:\\QtInstall\\6.2.4\\mingw_64\\include\\QtWidgets","-IC:\\QtInstall\\6.2.4\\mingw_64\\include\\QtGui","-IC:\\QtInstall\\6.2.4\\mingw_64\\include\\QtCore","-IC:\\ADW\\Dev\\C++\\QT\\MingWang\\02_Event\\Event\\build\\Desktop_Qt_6_2_4_MinGW_64_bit-Profile\\release","-IC:\\ADW\\Dev\\C++\\QT\\MingWang\\02_Event\\Event\\build\\Desktop_Qt_6_2_4_MinGW_64_bit-Profile","-IC:\\QtInstall\\6.2.4\\mingw_64\\mkspecs\\win32-g++","-isystem","C:\\QtInstall\\Tools\\mingw1120_64\\lib\\gcc\\x86_64-w64-mingw32\\11.2.0\\include\\c++","-isystem","C:\\QtInstall\\Tools\\mingw1120_64\\lib\\gcc\\x86_64-w64-mingw32\\11.2.0\\include\\c++\\x86_64-w64-mingw32","-isystem","C:\\QtInstall\\Tools\\mingw1120_64\\lib\\gcc\\x86_64-w64-mingw32\\11.2.0\\include\\c++\\backward","-isystem","C:\\QtInstall\\Tools\\QtCreator\\bin\\clang\\lib\\clang\\17\\include","-isystem","C:\\QtInstall\\Tools\\mingw1120_64\\x86_64-w64-mingw32\\include","-fmessage-length=0","-fdiagnostics-show-note-include-stack","-fretain-comments-from-system-headers","-fmacro-backtrace-limit=0","-ferror-limit=1000","-x","c++","C:\\ADW\\Dev\\C++\\QT\\MingWang\\02_Event\\src\\main.cpp"],"directory":"C:/ADW/Dev/C++/QT/MingWang/02_Event/Event/build/Desktop_Qt_6_2_4_MinGW_64_bit-Profile/.qtc_clangd","file":"C:/ADW/Dev/C++/QT/MingWang/02_Event/src/main.cpp"},{"arguments":["clang","-Wno-documentation-unknown-command","-Wno-unknown-warning-option","-Wno-unknown-pragmas","-nostdinc","-nostdinc++","-g","-std=gnu++1z","-Wall","-Wextra","-Wextra","-fexceptions","-mthreads","-fsyntax-only","-m64","--target=x86_64-w64-mingw32","-DUNICODE","-D_UNICODE","-DWIN32","-DMINGW_HAS_SECURE_API","-DQT_QML_DEBUG","-DQT_NO_DEBUG","-DQT_WIDGETS_LIB","-DQT_GUI_LIB","-DQT_CORE_LIB","-DQT_NEEDS_QMAIN","-DQ_CREATOR_RUN","-DQT_ANNOTATE_FUNCTION(x)=__attribute__((annotate(#x)))","-IC:\\QtInstall\\Tools\\QtCreator\\share\\qtcreator\\cplusplus\\wrappedMingwHeaders","-IC:\\QtInstall\\Tools\\QtCreator\\share\\qtcreator\\cplusplus\\wrappedQtHeaders","-IC:\\QtInstall\\Tools\\QtCreator\\share\\qtcreator\\cplusplus\\wrappedQtHeaders\\QtCore","-IC:\\ADW\\Dev\\C++\\QT\\MingWang\\02_Event\\src","-IC:\\QtInstall\\6.2.4\\mingw_64\\include","-IC:\\QtInstall\\6.2.4\\mingw_64\\include\\QtWidgets","-IC:\\QtInstall\\6.2.4\\mingw_64\\include\\QtGui","-IC:\\QtInstall\\6.2.4\\mingw_64\\include\\QtCore","-IC:\\ADW\\Dev\\C++\\QT\\MingWang\\02_Event\\Event\\build\\Desktop_Qt_6_2_4_MinGW_64_bit-Profile\\release","-IC:\\ADW\\Dev\\C++\\QT\\MingWang\\02_Event\\Event\\build\\Desktop_Qt_6_2_4_MinGW_64_bit-Profile","-IC:\\QtInstall\\6.2.4\\mingw_64\\mkspecs\\win32-g++","-isystem","C:\\QtInstall\\Tools\\mingw1120_64\\lib\\gcc\\x86_64-w64-mingw32\\11.2.0\\include\\c++","-isystem","C:\\QtInstall\\Tools\\mingw1120_64\\lib\\gcc\\x86_64-w64-mingw32\\11.2.0\\include\\c++\\x86_64-w64-mingw32","-isystem","C:\\QtInstall\\Tools\\mingw1120_64\\lib\\gcc\\x86_64-w64-mingw32\\11.2.0\\include\\c++\\backward","-isystem","C:\\QtInstall\\Tools\\QtCreator\\bin\\clang\\lib\\clang\\17\\include","-isystem","C:\\QtInstall\\Tools\\mingw1120_64\\x86_64-w64-mingw32\\include","-fmessage-length=0","-fdiagnostics-show-note-include-stack","-fretain-comments-from-system-headers","-fmacro-backtrace-limit=0","-ferror-limit=1000","-x","c++-header","C:\\ADW\\Dev\\C++\\QT\\MingWang\\02_Event\\src\\demo00_event.h"],"directory":"C:/ADW/Dev/C++/QT/MingWang/02_Event/Event/build/Desktop_Qt_6_2_4_MinGW_64_bit-Profile/.qtc_clangd","file":"C:/ADW/Dev/C++/QT/MingWang/02_Event/src/demo00_event.h"},{"arguments":["clang","-Wno-documentation-unknown-command","-Wno-unknown-warning-option","-Wno-unknown-pragmas","-nostdinc","-nostdinc++","-g","-std=gnu++1z","-Wall","-Wextra","-Wextra","-fexceptions","-mthreads","-fsyntax-only","-m64","--target=x86_64-w64-mingw32","-DUNICODE","-D_UNICODE","-DWIN32","-DMINGW_HAS_SECURE_API","-DQT_QML_DEBUG","-DQT_NO_DEBUG","-DQT_WIDGETS_LIB","-DQT_GUI_LIB","-DQT_CORE_LIB","-DQT_NEEDS_QMAIN","-DQ_CREATOR_RUN","-DQT_ANNOTATE_FUNCTION(x)=__attribute__((annotate(#x)))","-IC:\\QtInstall\\Tools\\QtCreator\\share\\qtcreator\\cplusplus\\wrappedMingwHeaders","-IC:\\QtInstall\\Tools\\QtCreator\\share\\qtcreator\\cplusplus\\wrappedQtHeaders","-IC:\\QtInstall\\Tools\\QtCreator\\share\\qtcreator\\cplusplus\\wrappedQtHeaders\\QtCore","-IC:\\ADW\\Dev\\C++\\QT\\MingWang\\02_Event\\src","-IC:\\QtInstall\\6.2.4\\mingw_64\\include","-IC:\\QtInstall\\6.2.4\\mingw_64\\include\\QtWidgets","-IC:\\QtInstall\\6.2.4\\mingw_64\\include\\QtGui","-IC:\\QtInstall\\6.2.4\\mingw_64\\include\\QtCore","-IC:\\ADW\\Dev\\C++\\QT\\MingWang\\02_Event\\Event\\build\\Desktop_Qt_6_2_4_MinGW_64_bit-Profile\\release","-IC:\\ADW\\Dev\\C++\\QT\\MingWang\\02_Event\\Event\\build\\Desktop_Qt_6_2_4_MinGW_64_bit-Profile","-IC:\\QtInstall\\6.2.4\\mingw_64\\mkspecs\\win32-g++","-isystem","C:\\QtInstall\\Tools\\mingw1120_64\\lib\\gcc\\x86_64-w64-mingw32\\11.2.0\\include\\c++","-isystem","C:\\QtInstall\\Tools\\mingw1120_64\\lib\\gcc\\x86_64-w64-mingw32\\11.2.0\\include\\c++\\x86_64-w64-mingw32","-isystem","C:\\QtInstall\\Tools\\mingw1120_64\\lib\\gcc\\x86_64-w64-mingw32\\11.2.0\\include\\c++\\backward","-isystem","C:\\QtInstall\\Tools\\QtCreator\\bin\\clang\\lib\\clang\\17\\include","-isystem","C:\\QtInstall\\Tools\\mingw1120_64\\x86_64-w64-mingw32\\include","-fmessage-length=0","-fdiagnostics-show-note-include-stack","-fretain-comments-from-system-headers","-fmacro-backtrace-limit=0","-ferror-limit=1000","-x","c++-header","C:\\ADW\\Dev\\C++\\QT\\MingWang\\02_Event\\src\\demo01_mouse_event.h"],"directory":"C:/ADW/Dev/C++/QT/MingWang/02_Event/Event/build/Desktop_Qt_6_2_4_MinGW_64_bit-Profile/.qtc_clangd","file":"C:/ADW/Dev/C++/QT/MingWang/02_Event/src/demo01_mouse_event.h"},{"arguments":["clang","-Wno-documentation-unknown-command","-Wno-unknown-warning-option","-Wno-unknown-pragmas","-nostdinc","-nostdinc++","-g","-std=gnu++1z","-Wall","-Wextra","-Wextra","-fexceptions","-mthreads","-fsyntax-only","-m64","--target=x86_64-w64-mingw32","-DUNICODE","-D_UNICODE","-DWIN32","-DMINGW_HAS_SECURE_API","-DQT_QML_DEBUG","-DQT_NO_DEBUG","-DQT_WIDGETS_LIB","-DQT_GUI_LIB","-DQT_CORE_LIB","-DQT_NEEDS_QMAIN","-DQ_CREATOR_RUN","-DQT_ANNOTATE_FUNCTION(x)=__attribute__((annotate(#x)))","-IC:\\QtInstall\\Tools\\QtCreator\\share\\qtcreator\\cplusplus\\wrappedMingwHeaders","-IC:\\QtInstall\\Tools\\QtCreator\\share\\qtcreator\\cplusplus\\wrappedQtHeaders","-IC:\\QtInstall\\Tools\\QtCreator\\share\\qtcreator\\cplusplus\\wrappedQtHeaders\\QtCore","-IC:\\ADW\\Dev\\C++\\QT\\MingWang\\02_Event\\src","-IC:\\QtInstall\\6.2.4\\mingw_64\\include","-IC:\\QtInstall\\6.2.4\\mingw_64\\include\\QtWidgets","-IC:\\QtInstall\\6.2.4\\mingw_64\\include\\QtGui","-IC:\\QtInstall\\6.2.4\\mingw_64\\include\\QtCore","-IC:\\ADW\\Dev\\C++\\QT\\MingWang\\02_Event\\Event\\build\\Desktop_Qt_6_2_4_MinGW_64_bit-Profile\\release","-IC:\\ADW\\Dev\\C++\\QT\\MingWang\\02_Event\\Event\\build\\Desktop_Qt_6_2_4_MinGW_64_bit-Profile","-IC:\\QtInstall\\6.2.4\\mingw_64\\mkspecs\\win32-g++","-isystem","C:\\QtInstall\\Tools\\mingw1120_64\\lib\\gcc\\x86_64-w64-mingw32\\11.2.0\\include\\c++","-isystem","C:\\QtInstall\\Tools\\mingw1120_64\\lib\\gcc\\x86_64-w64-mingw32\\11.2.0\\include\\c++\\x86_64-w64-mingw32","-isystem","C:\\QtInstall\\Tools\\mingw1120_64\\lib\\gcc\\x86_64-w64-mingw32\\11.2.0\\include\\c++\\backward","-isystem","C:\\QtInstall\\Tools\\QtCreator\\bin\\clang\\lib\\clang\\17\\include","-isystem","C:\\QtInstall\\Tools\\mingw1120_64\\x86_64-w64-mingw32\\include","-fmessage-length=0","-fdiagnostics-show-note-include-stack","-fretain-comments-from-system-headers","-fmacro-backtrace-limit=0","-ferror-limit=1000","-x","c++-header","C:\\ADW\\Dev\\C++\\QT\\MingWang\\02_Event\\src\\demo02_keyboard_event.h"],"directory":"C:/ADW/Dev/C++/QT/MingWang/02_Event/Event/build/Desktop_Qt_6_2_4_MinGW_64_bit-Profile/.qtc_clangd","file":"C:/ADW/Dev/C++/QT/MingWang/02_Event/src/demo02_keyboard_event.h"},{"arguments":["clang","-Wno-documentation-unknown-command","-Wno-unknown-warning-option","-Wno-unknown-pragmas","-nostdinc","-nostdinc++","-g","-std=gnu++1z","-Wall","-Wextra","-Wextra","-fexceptions","-mthreads","-fsyntax-only","-m64","--target=x86_64-w64-mingw32","-DUNICODE","-D_UNICODE","-DWIN32","-DMINGW_HAS_SECURE_API","-DQT_QML_DEBUG","-DQT_NO_DEBUG","-DQT_WIDGETS_LIB","-DQT_GUI_LIB","-DQT_CORE_LIB","-DQT_NEEDS_QMAIN","-DQ_CREATOR_RUN","-DQT_ANNOTATE_FUNCTION(x)=__attribute__((annotate(#x)))","-IC:\\QtInstall\\Tools\\QtCreator\\share\\qtcreator\\cplusplus\\wrappedMingwHeaders","-IC:\\QtInstall\\Tools\\QtCreator\\share\\qtcreator\\cplusplus\\wrappedQtHeaders","-IC:\\QtInstall\\Tools\\QtCreator\\share\\qtcreator\\cplusplus\\wrappedQtHeaders\\QtCore","-IC:\\ADW\\Dev\\C++\\QT\\MingWang\\02_Event\\src","-IC:\\QtInstall\\6.2.4\\mingw_64\\include","-IC:\\QtInstall\\6.2.4\\mingw_64\\include\\QtWidgets","-IC:\\QtInstall\\6.2.4\\mingw_64\\include\\QtGui","-IC:\\QtInstall\\6.2.4\\mingw_64\\include\\QtCore","-IC:\\ADW\\Dev\\C++\\QT\\MingWang\\02_Event\\Event\\build\\Desktop_Qt_6_2_4_MinGW_64_bit-Profile\\release","-IC:\\ADW\\Dev\\C++\\QT\\MingWang\\02_Event\\Event\\build\\Desktop_Qt_6_2_4_MinGW_64_bit-Profile","-IC:\\QtInstall\\6.2.4\\mingw_64\\mkspecs\\win32-g++","-isystem","C:\\QtInstall\\Tools\\mingw1120_64\\lib\\gcc\\x86_64-w64-mingw32\\11.2.0\\include\\c++","-isystem","C:\\QtInstall\\Tools\\mingw1120_64\\lib\\gcc\\x86_64-w64-mingw32\\11.2.0\\include\\c++\\x86_64-w64-mingw32","-isystem","C:\\QtInstall\\Tools\\mingw1120_64\\lib\\gcc\\x86_64-w64-mingw32\\11.2.0\\include\\c++\\backward","-isystem","C:\\QtInstall\\Tools\\QtCreator\\bin\\clang\\lib\\clang\\17\\include","-isystem","C:\\QtInstall\\Tools\\mingw1120_64\\x86_64-w64-mingw32\\include","-fmessage-length=0","-fdiagnostics-show-note-include-stack","-fretain-comments-from-system-headers","-fmacro-backtrace-limit=0","-ferror-limit=1000","-x","c++-header","C:\\ADW\\Dev\\C++\\QT\\MingWang\\02_Event\\src\\demo03_timer_event.h"],"directory":"C:/ADW/Dev/C++/QT/MingWang/02_Event/Event/build/Desktop_Qt_6_2_4_MinGW_64_bit-Profile/.qtc_clangd","file":"C:/ADW/Dev/C++/QT/MingWang/02_Event/src/demo03_timer_event.h"},{"arguments":["clang","-Wno-documentation-unknown-command","-Wno-unknown-warning-option","-Wno-unknown-pragmas","-nostdinc","-nostdinc++","-g","-std=gnu++1z","-Wall","-Wextra","-Wextra","-fexceptions","-mthreads","-fsyntax-only","-m64","--target=x86_64-w64-mingw32","-DUNICODE","-D_UNICODE","-DWIN32","-DMINGW_HAS_SECURE_API","-DQT_QML_DEBUG","-DQT_NO_DEBUG","-DQT_WIDGETS_LIB","-DQT_GUI_LIB","-DQT_CORE_LIB","-DQT_NEEDS_QMAIN","-DQ_CREATOR_RUN","-DQT_ANNOTATE_FUNCTION(x)=__attribute__((annotate(#x)))","-IC:\\QtInstall\\Tools\\QtCreator\\share\\qtcreator\\cplusplus\\wrappedMingwHeaders","-IC:\\QtInstall\\Tools\\QtCreator\\share\\qtcreator\\cplusplus\\wrappedQtHeaders","-IC:\\QtInstall\\Tools\\QtCreator\\share\\qtcreator\\cplusplus\\wrappedQtHeaders\\QtCore","-IC:\\ADW\\Dev\\C++\\QT\\MingWang\\02_Event\\src","-IC:\\QtInstall\\6.2.4\\mingw_64\\include","-IC:\\QtInstall\\6.2.4\\mingw_64\\include\\QtWidgets","-IC:\\QtInstall\\6.2.4\\mingw_64\\include\\QtGui","-IC:\\QtInstall\\6.2.4\\mingw_64\\include\\QtCore","-IC:\\ADW\\Dev\\C++\\QT\\MingWang\\02_Event\\Event\\build\\Desktop_Qt_6_2_4_MinGW_64_bit-Profile\\release","-IC:\\ADW\\Dev\\C++\\QT\\MingWang\\02_Event\\Event\\build\\Desktop_Qt_6_2_4_MinGW_64_bit-Profile","-IC:\\QtInstall\\6.2.4\\mingw_64\\mkspecs\\win32-g++","-isystem","C:\\QtInstall\\Tools\\mingw1120_64\\lib\\gcc\\x86_64-w64-mingw32\\11.2.0\\include\\c++","-isystem","C:\\QtInstall\\Tools\\mingw1120_64\\lib\\gcc\\x86_64-w64-mingw32\\11.2.0\\include\\c++\\x86_64-w64-mingw32","-isystem","C:\\QtInstall\\Tools\\mingw1120_64\\lib\\gcc\\x86_64-w64-mingw32\\11.2.0\\include\\c++\\backward","-isystem","C:\\QtInstall\\Tools\\QtCreator\\bin\\clang\\lib\\clang\\17\\include","-isystem","C:\\QtInstall\\Tools\\mingw1120_64\\x86_64-w64-mingw32\\include","-fmessage-length=0","-fdiagnostics-show-note-include-stack","-fretain-comments-from-system-headers","-fmacro-backtrace-limit=0","-ferror-limit=1000","-x","c++-header","C:\\ADW\\Dev\\C++\\QT\\MingWang\\02_Event\\src\\demo04_drag_event.h"],"directory":"C:/ADW/Dev/C++/QT/MingWang/02_Event/Event/build/Desktop_Qt_6_2_4_MinGW_64_bit-Profile/.qtc_clangd","file":"C:/ADW/Dev/C++/QT/MingWang/02_Event/src/demo04_drag_event.h"},{"arguments":["clang","-Wno-documentation-unknown-command","-Wno-unknown-warning-option","-Wno-unknown-pragmas","-nostdinc","-nostdinc++","-g","-std=gnu++1z","-Wall","-Wextra","-Wextra","-fexceptions","-mthreads","-fsyntax-only","-m64","--target=x86_64-w64-mingw32","-DUNICODE","-D_UNICODE","-DWIN32","-DMINGW_HAS_SECURE_API","-DQT_QML_DEBUG","-DQT_NO_DEBUG","-DQT_WIDGETS_LIB","-DQT_GUI_LIB","-DQT_CORE_LIB","-DQT_NEEDS_QMAIN","-DQ_CREATOR_RUN","-DQT_ANNOTATE_FUNCTION(x)=__attribute__((annotate(#x)))","-IC:\\QtInstall\\Tools\\QtCreator\\share\\qtcreator\\cplusplus\\wrappedMingwHeaders","-IC:\\QtInstall\\Tools\\QtCreator\\share\\qtcreator\\cplusplus\\wrappedQtHeaders","-IC:\\QtInstall\\Tools\\QtCreator\\share\\qtcreator\\cplusplus\\wrappedQtHeaders\\QtCore","-IC:\\ADW\\Dev\\C++\\QT\\MingWang\\02_Event\\src","-IC:\\QtInstall\\6.2.4\\mingw_64\\include","-IC:\\QtInstall\\6.2.4\\mingw_64\\include\\QtWidgets","-IC:\\QtInstall\\6.2.4\\mingw_64\\include\\QtGui","-IC:\\QtInstall\\6.2.4\\mingw_64\\include\\QtCore","-IC:\\ADW\\Dev\\C++\\QT\\MingWang\\02_Event\\Event\\build\\Desktop_Qt_6_2_4_MinGW_64_bit-Profile\\release","-IC:\\ADW\\Dev\\C++\\QT\\MingWang\\02_Event\\Event\\build\\Desktop_Qt_6_2_4_MinGW_64_bit-Profile","-IC:\\QtInstall\\6.2.4\\mingw_64\\mkspecs\\win32-g++","-isystem","C:\\QtInstall\\Tools\\mingw1120_64\\lib\\gcc\\x86_64-w64-mingw32\\11.2.0\\include\\c++","-isystem","C:\\QtInstall\\Tools\\mingw1120_64\\lib\\gcc\\x86_64-w64-mingw32\\11.2.0\\include\\c++\\x86_64-w64-mingw32","-isystem","C:\\QtInstall\\Tools\\mingw1120_64\\lib\\gcc\\x86_64-w64-mingw32\\11.2.0\\include\\c++\\backward","-isystem","C:\\QtInstall\\Tools\\QtCreator\\bin\\clang\\lib\\clang\\17\\include","-isystem","C:\\QtInstall\\Tools\\mingw1120_64\\x86_64-w64-mingw32\\include","-fmessage-length=0","-fdiagnostics-show-note-include-stack","-fretain-comments-from-system-headers","-fmacro-backtrace-limit=0","-ferror-limit=1000","-x","c++-header","C:\\ADW\\Dev\\C++\\QT\\MingWang\\02_Event\\src\\demo05_paint_event.h"],"directory":"C:/ADW/Dev/C++/QT/MingWang/02_Event/Event/build/Desktop_Qt_6_2_4_MinGW_64_bit-Profile/.qtc_clangd","file":"C:/ADW/Dev/C++/QT/MingWang/02_Event/src/demo05_paint_event.h"},{"arguments":["clang","-Wno-documentation-unknown-command","-Wno-unknown-warning-option","-Wno-unknown-pragmas","-nostdinc","-nostdinc++","-g","-std=gnu++1z","-Wall","-Wextra","-Wextra","-fexceptions","-mthreads","-fsyntax-only","-m64","--target=x86_64-w64-mingw32","-DUNICODE","-D_UNICODE","-DWIN32","-DMINGW_HAS_SECURE_API","-DQT_QML_DEBUG","-DQT_NO_DEBUG","-DQT_WIDGETS_LIB","-DQT_GUI_LIB","-DQT_CORE_LIB","-DQT_NEEDS_QMAIN","-DQ_CREATOR_RUN","-DQT_ANNOTATE_FUNCTION(x)=__attribute__((annotate(#x)))","-IC:\\QtInstall\\Tools\\QtCreator\\share\\qtcreator\\cplusplus\\wrappedMingwHeaders","-IC:\\QtInstall\\Tools\\QtCreator\\share\\qtcreator\\cplusplus\\wrappedQtHeaders","-IC:\\QtInstall\\Tools\\QtCreator\\share\\qtcreator\\cplusplus\\wrappedQtHeaders\\QtCore","-IC:\\ADW\\Dev\\C++\\QT\\MingWang\\02_Event\\src","-IC:\\QtInstall\\6.2.4\\mingw_64\\include","-IC:\\QtInstall\\6.2.4\\mingw_64\\include\\QtWidgets","-IC:\\QtInstall\\6.2.4\\mingw_64\\include\\QtGui","-IC:\\QtInstall\\6.2.4\\mingw_64\\include\\QtCore","-IC:\\ADW\\Dev\\C++\\QT\\MingWang\\02_Event\\Event\\build\\Desktop_Qt_6_2_4_MinGW_64_bit-Profile\\release","-IC:\\ADW\\Dev\\C++\\QT\\MingWang\\02_Event\\Event\\build\\Desktop_Qt_6_2_4_MinGW_64_bit-Profile","-IC:\\QtInstall\\6.2.4\\mingw_64\\mkspecs\\win32-g++","-isystem","C:\\QtInstall\\Tools\\mingw1120_64\\lib\\gcc\\x86_64-w64-mingw32\\11.2.0\\include\\c++","-isystem","C:\\QtInstall\\Tools\\mingw1120_64\\lib\\gcc\\x86_64-w64-mingw32\\11.2.0\\include\\c++\\x86_64-w64-mingw32","-isystem","C:\\QtInstall\\Tools\\mingw1120_64\\lib\\gcc\\x86_64-w64-mingw32\\11.2.0\\include\\c++\\backward","-isystem","C:\\QtInstall\\Tools\\QtCreator\\bin\\clang\\lib\\clang\\17\\include","-isystem","C:\\QtInstall\\Tools\\mingw1120_64\\x86_64-w64-mingw32\\include","-fmessage-length=0","-fdiagnostics-show-note-include-stack","-fretain-comments-from-system-headers","-fmacro-backtrace-limit=0","-ferror-limit=1000","-x","c++-header","C:\\ADW\\Dev\\C++\\QT\\MingWang\\02_Event\\src\\demo06_context_menu_event.h"],"directory":"C:/ADW/Dev/C++/QT/MingWang/02_Event/Event/build/Desktop_Qt_6_2_4_MinGW_64_bit-Profile/.qtc_clangd","file":"C:/ADW/Dev/C++/QT/MingWang/02_Event/src/demo06_context_menu_event.h"},{"arguments":["clang","-Wno-documentation-unknown-command","-Wno-unknown-warning-option","-Wno-unknown-pragmas","-nostdinc","-nostdinc++","-g","-std=gnu++1z","-Wall","-Wextra","-Wextra","-fexceptions","-mthreads","-fsyntax-only","-m64","--target=x86_64-w64-mingw32","-DUNICODE","-D_UNICODE","-DWIN32","-DMINGW_HAS_SECURE_API","-DQT_QML_DEBUG","-DQT_NO_DEBUG","-DQT_WIDGETS_LIB","-DQT_GUI_LIB","-DQT_CORE_LIB","-DQT_NEEDS_QMAIN","-DQ_CREATOR_RUN","-DQT_ANNOTATE_FUNCTION(x)=__attribute__((annotate(#x)))","-IC:\\QtInstall\\Tools\\QtCreator\\share\\qtcreator\\cplusplus\\wrappedMingwHeaders","-IC:\\QtInstall\\Tools\\QtCreator\\share\\qtcreator\\cplusplus\\wrappedQtHeaders","-IC:\\QtInstall\\Tools\\QtCreator\\share\\qtcreator\\cplusplus\\wrappedQtHeaders\\QtCore","-IC:\\ADW\\Dev\\C++\\QT\\MingWang\\02_Event\\src","-IC:\\QtInstall\\6.2.4\\mingw_64\\include","-IC:\\QtInstall\\6.2.4\\mingw_64\\include\\QtWidgets","-IC:\\QtInstall\\6.2.4\\mingw_64\\include\\QtGui","-IC:\\QtInstall\\6.2.4\\mingw_64\\include\\QtCore","-IC:\\ADW\\Dev\\C++\\QT\\MingWang\\02_Event\\Event\\build\\Desktop_Qt_6_2_4_MinGW_64_bit-Profile\\release","-IC:\\ADW\\Dev\\C++\\QT\\MingWang\\02_Event\\Event\\build\\Desktop_Qt_6_2_4_MinGW_64_bit-Profile","-IC:\\QtInstall\\6.2.4\\mingw_64\\mkspecs\\win32-g++","-isystem","C:\\QtInstall\\Tools\\mingw1120_64\\lib\\gcc\\x86_64-w64-mingw32\\11.2.0\\include\\c++","-isystem","C:\\QtInstall\\Tools\\mingw1120_64\\lib\\gcc\\x86_64-w64-mingw32\\11.2.0\\include\\c++\\x86_64-w64-mingw32","-isystem","C:\\QtInstall\\Tools\\mingw1120_64\\lib\\gcc\\x86_64-w64-mingw32\\11.2.0\\include\\c++\\backward","-isystem","C:\\QtInstall\\Tools\\QtCreator\\bin\\clang\\lib\\clang\\17\\include","-isystem","C:\\QtInstall\\Tools\\mingw1120_64\\x86_64-w64-mingw32\\include","-fmessage-length=0","-fdiagnostics-show-note-include-stack","-fretain-comments-from-system-headers","-fmacro-backtrace-limit=0","-ferror-limit=1000","-x","c++-header","C:\\ADW\\Dev\\C++\\QT\\MingWang\\02_Event\\src\\demo07_event_propagate_process.h"],"directory":"C:/ADW/Dev/C++/QT/MingWang/02_Event/Event/build/Desktop_Qt_6_2_4_MinGW_64_bit-Profile/.qtc_clangd","file":"C:/ADW/Dev/C++/QT/MingWang/02_Event/src/demo07_event_propagate_process.h"},{"arguments":["clang","-Wno-documentation-unknown-command","-Wno-unknown-warning-option","-Wno-unknown-pragmas","-nostdinc","-nostdinc++","-g","-std=gnu++1z","-Wall","-Wextra","-Wextra","-fexceptions","-mthreads","-fsyntax-only","-m64","--target=x86_64-w64-mingw32","-DUNICODE","-D_UNICODE","-DWIN32","-DMINGW_HAS_SECURE_API","-DQT_QML_DEBUG","-DQT_NO_DEBUG","-DQT_WIDGETS_LIB","-DQT_GUI_LIB","-DQT_CORE_LIB","-DQT_NEEDS_QMAIN","-DQ_CREATOR_RUN","-DQT_ANNOTATE_FUNCTION(x)=__attribute__((annotate(#x)))","-IC:\\QtInstall\\Tools\\QtCreator\\share\\qtcreator\\cplusplus\\wrappedMingwHeaders","-IC:\\QtInstall\\Tools\\QtCreator\\share\\qtcreator\\cplusplus\\wrappedQtHeaders","-IC:\\QtInstall\\Tools\\QtCreator\\share\\qtcreator\\cplusplus\\wrappedQtHeaders\\QtCore","-IC:\\ADW\\Dev\\C++\\QT\\MingWang\\02_Event\\src","-IC:\\QtInstall\\6.2.4\\mingw_64\\include","-IC:\\QtInstall\\6.2.4\\mingw_64\\include\\QtWidgets","-IC:\\QtInstall\\6.2.4\\mingw_64\\include\\QtGui","-IC:\\QtInstall\\6.2.4\\mingw_64\\include\\QtCore","-IC:\\ADW\\Dev\\C++\\QT\\MingWang\\02_Event\\Event\\build\\Desktop_Qt_6_2_4_MinGW_64_bit-Profile\\release","-IC:\\ADW\\Dev\\C++\\QT\\MingWang\\02_Event\\Event\\build\\Desktop_Qt_6_2_4_MinGW_64_bit-Profile","-IC:\\QtInstall\\6.2.4\\mingw_64\\mkspecs\\win32-g++","-isystem","C:\\QtInstall\\Tools\\mingw1120_64\\lib\\gcc\\x86_64-w64-mingw32\\11.2.0\\include\\c++","-isystem","C:\\QtInstall\\Tools\\mingw1120_64\\lib\\gcc\\x86_64-w64-mingw32\\11.2.0\\include\\c++\\x86_64-w64-mingw32","-isystem","C:\\QtInstall\\Tools\\mingw1120_64\\lib\\gcc\\x86_64-w64-mingw32\\11.2.0\\include\\c++\\backward","-isystem","C:\\QtInstall\\Tools\\QtCreator\\bin\\clang\\lib\\clang\\17\\include","-isystem","C:\\QtInstall\\Tools\\mingw1120_64\\x86_64-w64-mingw32\\include","-fmessage-length=0","-fdiagnostics-show-note-include-stack","-fretain-comments-from-system-headers","-fmacro-backtrace-limit=0","-ferror-limit=1000","-x","c++-header","C:\\ADW\\Dev\\C++\\QT\\MingWang\\02_Event\\src\\demobase.h"],"directory":"C:/ADW/Dev/C++/QT/MingWang/02_Event/Event/build/Desktop_Qt_6_2_4_MinGW_64_bit-Profile/.qtc_clangd","file":"C:/ADW/Dev/C++/QT/MingWang/02_Event/src/demobase.h"}]